pjreports/__init__.py
pjreports/report.py
pjreports/reportManager.py
pjreports/settings.py
pjreports/java/__init__.py
pjreports/java/jpreports-java.jar
pjreports/managejrxml/__init__.py
pjreports/managejrxml/image.py
pjreports/managejrxml/parameter.py
pjreports/managejrxml/text.py
pjreports/utils/__init__.py
pjreports/utils/decorators.py
pjreports/utils/pdf.py
pjreports-0.0.1a12.dist-info/METADATA
pjreports-0.0.1a12.dist-info/RECORD
pjreports-0.0.1a12.dist-info/WHEEL
pjreports-0.0.1a12.dist-info/top_level.txt
